README.md
setup.py
ai_maze.egg-info/PKG-INFO
ai_maze.egg-info/SOURCES.txt
ai_maze.egg-info/dependency_links.txt
ai_maze.egg-info/requires.txt
ai_maze.egg-info/top_level.txt
generator/Main.py
generator/__init__.py
generator/subpackage/MazeGen.py
generator/subpackage/__init__.py
main-pkg/Main.py
main-pkg/__init__.py
subclass/BreadthFirst.py
subclass/DepthFirst.py
subclass/Node.py
subclass/__init__.py